kaggleupload/__init__.py
kaggleupload/cli.py
kaggleupload/code.py
kaggleupload-0.1.0.dist-info/LICENSE
kaggleupload-0.1.0.dist-info/METADATA
kaggleupload-0.1.0.dist-info/WHEEL
kaggleupload-0.1.0.dist-info/entry_points.txt
kaggleupload-0.1.0.dist-info/top_level.txt
kaggleupload-0.1.0.dist-info/RECORD
